py.typed
codat_sync_for_payables/__init__.py
codat_sync_for_payables/_hooks/__init__.py
codat_sync_for_payables/_hooks/registration.py
codat_sync_for_payables/_hooks/sdkhooks.py
codat_sync_for_payables/_hooks/types.py
codat_sync_for_payables/_version.py
codat_sync_for_payables/bank_accounts.py
codat_sync_for_payables/basesdk.py
codat_sync_for_payables/bill_payments.py
codat_sync_for_payables/bills.py
codat_sync_for_payables/companies.py
codat_sync_for_payables/company_information.py
codat_sync_for_payables/connections.py
codat_sync_for_payables/httpclient.py
codat_sync_for_payables/models/errors/__init__.py
codat_sync_for_payables/models/errors/errormessage.py
codat_sync_for_payables/models/errors/sdkerror.py
codat_sync_for_payables/models/operations/__init__.py
codat_sync_for_payables/models/operations/create_bank_account.py
codat_sync_for_payables/models/operations/create_bill.py
codat_sync_for_payables/models/operations/create_bill_payment.py
codat_sync_for_payables/models/operations/create_connection.py
codat_sync_for_payables/models/operations/create_supplier.py
codat_sync_for_payables/models/operations/delete_company.py
codat_sync_for_payables/models/operations/delete_connection.py
codat_sync_for_payables/models/operations/download_bill_attachment.py
codat_sync_for_payables/models/operations/get_company.py
codat_sync_for_payables/models/operations/get_company_information.py
codat_sync_for_payables/models/operations/get_connection.py
codat_sync_for_payables/models/operations/get_mapping_options_bills.py
codat_sync_for_payables/models/operations/get_mapping_options_payments.py
codat_sync_for_payables/models/operations/list_bill_attachments.py
codat_sync_for_payables/models/operations/list_bills.py
codat_sync_for_payables/models/operations/list_companies.py
codat_sync_for_payables/models/operations/list_connections.py
codat_sync_for_payables/models/operations/list_suppliers.py
codat_sync_for_payables/models/operations/unlink_connection.py
codat_sync_for_payables-8.0.3.dist-info/METADATA
codat_sync_for_payables-8.0.3.dist-info/WHEEL
codat_sync_for_payables-8.0.3.dist-info/RECORD
